{
    "total": [
        {
            "id": "61554417757153",
            "count": 0
        },
        {
            "id": "100094084096155",
            "count": 0
        },
        {
            "id": "61556309255001",
            "count": 0
        },
        {
            "id": "61555819021860",
            "count": 0
        },
        {
            "id": "61552626372533",
            "count": 0
        },
        {
            "id": "61554500413279",
            "count": 9
        },
        {
            "id": "61551244611327",
            "count": 1
        },
        {
            "id": "100093463959638",
            "count": 0
        },
        {
            "id": "61556986434152",
            "count": 0
        },
        {
            "id": "100007634802847",
            "count": 0
        },
        {
            "id": "100092331823627",
            "count": 0
        },
        {
            "id": "61550692794754",
            "count": 0
        },
        {
            "id": "61552353291750",
            "count": 0
        },
        {
            "id": "61554873957944",
            "count": 0
        },
        {
            "id": "100080672973218",
            "count": 0
        },
        {
            "id": "61555966720585",
            "count": 0
        },
        {
            "id": "100085259528865",
            "count": 0
        },
        {
            "id": "61554675710700",
            "count": 34
        },
        {
            "id": "61554928105224",
            "count": 0
        },
        {
            "id": "100078889791326",
            "count": 0
        },
        {
            "id": "100082078660502",
            "count": 0
        },
        {
            "id": "100093666380820",
            "count": 3
        },
        {
            "id": "100085934521377",
            "count": 0
        },
        {
            "id": "100088977319563",
            "count": 0
        },
        {
            "id": "100089897166596",
            "count": 0
        },
        {
            "id": "61552868182165",
            "count": 0
        },
        {
            "id": "100093352148971",
            "count": 0
        },
        {
            "id": "61555882580452",
            "count": 0
        },
        {
            "id": "61553342486430",
            "count": 0
        },
        {
            "id": "61556017607027",
            "count": 0
        },
        {
            "id": "100087371977776",
            "count": 0
        },
        {
            "id": "100081263356361",
            "count": 0
        },
        {
            "id": "100095396597874",
            "count": 0
        },
        {
            "id": "100083940201436",
            "count": 0
        },
        {
            "id": "61551995573780",
            "count": 0
        },
        {
            "id": "61556891618280",
            "count": 0
        },
        {
            "id": "61550497393470",
            "count": 0
        },
        {
            "id": "100090690968592",
            "count": 0
        },
        {
            "id": "61551361058912",
            "count": 0
        },
        {
            "id": "61551992015960",
            "count": 0
        },
        {
            "id": "100079300612769",
            "count": 0
        },
        {
            "id": "61554676625535",
            "count": 0
        },
        {
            "id": "100076805960914",
            "count": 0
        },
        {
            "id": "100090055263711",
            "count": 0
        },
        {
            "id": "100092671497583",
            "count": 0
        },
        {
            "id": "61551053635413",
            "count": 0
        },
        {
            "id": "100091515476589",
            "count": 11
        },
        {
            "id": "61550902924150",
            "count": 0
        },
        {
            "id": "100082114500549",
            "count": 0
        },
        {
            "id": "100094921357761",
            "count": 0
        },
        {
            "id": "100093170903843",
            "count": 0
        },
        {
            "id": "61552302874397",
            "count": 0
        },
        {
            "id": "100093989171898",
            "count": 0
        },
        {
            "id": "61551081923004",
            "count": 0
        },
        {
            "id": "61557584044524",
            "count": 0
        },
        {
            "id": "100000622123483",
            "count": 0
        },
        {
            "id": "61557364617384",
            "count": 0
        },
        {
            "id": "61557579075059",
            "count": 0
        },
        {
            "id": "61555209135363",
            "count": 0
        },
        {
            "id": "61557589061861",
            "count": 0
        },
        {
            "id": "100023401686179",
            "count": 0
        },
        {
            "id": "61558474401296",
            "count": 1
        },
        {
            "id": "100085746765361",
            "count": 11
        },
        {
            "id": "61554329973761",
            "count": 0
        },
        {
            "id": "61555599504792",
            "count": 0
        },
        {
            "id": "61558624210490",
            "count": 0
        },
        {
            "id": "61557909327852",
            "count": 0
        },
        {
            "id": "61551391348333",
            "count": 35
        },
        {
            "id": "100084773303548",
            "count": 0
        },
        {
            "id": "100087893475366",
            "count": 0
        },
        {
            "id": "100092017008204",
            "count": 0
        },
        {
            "id": "100090142852075",
            "count": 0
        },
        {
            "id": "100084378103510",
            "count": 0
        },
        {
            "id": "61559545493006",
            "count": 0
        },
        {
            "id": "61559532861411",
            "count": 0
        },
        {
            "id": "100093624729133",
            "count": 0
        },
        {
            "id": "100093051642489",
            "count": 0
        },
        {
            "id": "61552411872970",
            "count": 11
        },
        {
            "id": "100089205454472",
            "count": 0
        },
        {
            "id": "100094760988409",
            "count": 0
        },
        {
            "id": "61559070333013",
            "count": 0
        },
        {
            "id": "100056611101316",
            "count": 0
        },
        {
            "id": "61557664555309",
            "count": 0
        },
        {
            "id": "100091971812462",
            "count": 0
        },
        {
            "id": "100073758246102",
            "count": 0
        },
        {
            "id": "61559777633272",
            "count": 35
        },
        {
            "id": "61559856307178",
            "count": 0
        },
        {
            "id": "61555962316369",
            "count": 0
        },
        {
            "id": "61550740599649",
            "count": 0
        },
        {
            "id": "61555856079604",
            "count": 0
        },
        {
            "id": "61557169396593",
            "count": 0
        },
        {
            "id": "61554657060164",
            "count": 0
        },
        {
            "id": "61550314954495",
            "count": 0
        },
        {
            "id": "61556358576535",
            "count": 0
        },
        {
            "id": "61558192455401",
            "count": 12
        },
        {
            "id": "61553928123305",
            "count": 0
        },
        {
            "id": "100077082825707",
            "count": 0
        },
        {
            "id": "61557623488042",
            "count": 35
        },
        {
            "id": "61560523033775",
            "count": 2
        },
        {
            "id": "61557990792452",
            "count": 2
        },
        {
            "id": "61557862673264",
            "count": 16
        },
        {
            "id": "61550555437615",
            "count": 4
        },
        {
            "id": "61555707685869",
            "count": 10
        }
    ],
    "week": [
        {
            "id": "61554417757153",
            "count": 0
        },
        {
            "id": "100094084096155",
            "count": 0
        },
        {
            "id": "61556309255001",
            "count": 0
        },
        {
            "id": "61555819021860",
            "count": 0
        },
        {
            "id": "61552626372533",
            "count": 0
        },
        {
            "id": "61554500413279",
            "count": 9
        },
        {
            "id": "61551244611327",
            "count": 1
        },
        {
            "id": "100093463959638",
            "count": 0
        },
        {
            "id": "61556986434152",
            "count": 0
        },
        {
            "id": "100007634802847",
            "count": 0
        },
        {
            "id": "100092331823627",
            "count": 0
        },
        {
            "id": "61550692794754",
            "count": 0
        },
        {
            "id": "61552353291750",
            "count": 0
        },
        {
            "id": "61554873957944",
            "count": 0
        },
        {
            "id": "100080672973218",
            "count": 0
        },
        {
            "id": "61555966720585",
            "count": 0
        },
        {
            "id": "100085259528865",
            "count": 0
        },
        {
            "id": "61554675710700",
            "count": 34
        },
        {
            "id": "61554928105224",
            "count": 0
        },
        {
            "id": "100078889791326",
            "count": 0
        },
        {
            "id": "100082078660502",
            "count": 0
        },
        {
            "id": "100093666380820",
            "count": 3
        },
        {
            "id": "100085934521377",
            "count": 0
        },
        {
            "id": "100088977319563",
            "count": 0
        },
        {
            "id": "100089897166596",
            "count": 0
        },
        {
            "id": "61552868182165",
            "count": 0
        },
        {
            "id": "100093352148971",
            "count": 0
        },
        {
            "id": "61555882580452",
            "count": 0
        },
        {
            "id": "61553342486430",
            "count": 0
        },
        {
            "id": "61556017607027",
            "count": 0
        },
        {
            "id": "100087371977776",
            "count": 0
        },
        {
            "id": "100081263356361",
            "count": 0
        },
        {
            "id": "100095396597874",
            "count": 0
        },
        {
            "id": "100083940201436",
            "count": 0
        },
        {
            "id": "61551995573780",
            "count": 0
        },
        {
            "id": "61556891618280",
            "count": 0
        },
        {
            "id": "61550497393470",
            "count": 0
        },
        {
            "id": "100090690968592",
            "count": 0
        },
        {
            "id": "61551361058912",
            "count": 0
        },
        {
            "id": "61551992015960",
            "count": 0
        },
        {
            "id": "100079300612769",
            "count": 0
        },
        {
            "id": "61554676625535",
            "count": 0
        },
        {
            "id": "100076805960914",
            "count": 0
        },
        {
            "id": "100090055263711",
            "count": 0
        },
        {
            "id": "100092671497583",
            "count": 0
        },
        {
            "id": "61551053635413",
            "count": 0
        },
        {
            "id": "100091515476589",
            "count": 11
        },
        {
            "id": "61550902924150",
            "count": 0
        },
        {
            "id": "100082114500549",
            "count": 0
        },
        {
            "id": "100094921357761",
            "count": 0
        },
        {
            "id": "100093170903843",
            "count": 0
        },
        {
            "id": "61552302874397",
            "count": 0
        },
        {
            "id": "100093989171898",
            "count": 0
        },
        {
            "id": "61551081923004",
            "count": 0
        },
        {
            "id": "61557584044524",
            "count": 0
        },
        {
            "id": "100000622123483",
            "count": 0
        },
        {
            "id": "61557364617384",
            "count": 0
        },
        {
            "id": "61557579075059",
            "count": 0
        },
        {
            "id": "61555209135363",
            "count": 0
        },
        {
            "id": "61557589061861",
            "count": 0
        },
        {
            "id": "100023401686179",
            "count": 0
        },
        {
            "id": "61558474401296",
            "count": 1
        },
        {
            "id": "100085746765361",
            "count": 11
        },
        {
            "id": "61554329973761",
            "count": 0
        },
        {
            "id": "61555599504792",
            "count": 0
        },
        {
            "id": "61558624210490",
            "count": 0
        },
        {
            "id": "61557909327852",
            "count": 0
        },
        {
            "id": "61551391348333",
            "count": 35
        },
        {
            "id": "100084773303548",
            "count": 0
        },
        {
            "id": "100087893475366",
            "count": 0
        },
        {
            "id": "100092017008204",
            "count": 0
        },
        {
            "id": "100090142852075",
            "count": 0
        },
        {
            "id": "100084378103510",
            "count": 0
        },
        {
            "id": "61559545493006",
            "count": 0
        },
        {
            "id": "61559532861411",
            "count": 0
        },
        {
            "id": "100093624729133",
            "count": 0
        },
        {
            "id": "100093051642489",
            "count": 0
        },
        {
            "id": "61552411872970",
            "count": 11
        },
        {
            "id": "100089205454472",
            "count": 0
        },
        {
            "id": "100094760988409",
            "count": 0
        },
        {
            "id": "61559070333013",
            "count": 0
        },
        {
            "id": "100056611101316",
            "count": 0
        },
        {
            "id": "61557664555309",
            "count": 0
        },
        {
            "id": "100091971812462",
            "count": 0
        },
        {
            "id": "100073758246102",
            "count": 0
        },
        {
            "id": "61559777633272",
            "count": 35
        },
        {
            "id": "61559856307178",
            "count": 0
        },
        {
            "id": "61555962316369",
            "count": 0
        },
        {
            "id": "61550740599649",
            "count": 0
        },
        {
            "id": "61555856079604",
            "count": 0
        },
        {
            "id": "61557169396593",
            "count": 0
        },
        {
            "id": "61554657060164",
            "count": 0
        },
        {
            "id": "61550314954495",
            "count": 0
        },
        {
            "id": "61556358576535",
            "count": 0
        },
        {
            "id": "61558192455401",
            "count": 12
        },
        {
            "id": "61553928123305",
            "count": 0
        },
        {
            "id": "100077082825707",
            "count": 0
        },
        {
            "id": "61557623488042",
            "count": 35
        },
        {
            "id": "61560523033775",
            "count": 2
        },
        {
            "id": "61557990792452",
            "count": 2
        },
        {
            "id": "61557862673264",
            "count": 16
        },
        {
            "id": "61550555437615",
            "count": 4
        },
        {
            "id": "61555707685869",
            "count": 10
        }
    ],
    "day": [
        {
            "id": "61554417757153",
            "count": 0
        },
        {
            "id": "100094084096155",
            "count": 0
        },
        {
            "id": "61556309255001",
            "count": 0
        },
        {
            "id": "61555819021860",
            "count": 0
        },
        {
            "id": "61552626372533",
            "count": 0
        },
        {
            "id": "61554500413279",
            "count": 9
        },
        {
            "id": "61551244611327",
            "count": 1
        },
        {
            "id": "100093463959638",
            "count": 0
        },
        {
            "id": "61556986434152",
            "count": 0
        },
        {
            "id": "100007634802847",
            "count": 0
        },
        {
            "id": "100092331823627",
            "count": 0
        },
        {
            "id": "61550692794754",
            "count": 0
        },
        {
            "id": "61552353291750",
            "count": 0
        },
        {
            "id": "61554873957944",
            "count": 0
        },
        {
            "id": "100080672973218",
            "count": 0
        },
        {
            "id": "61555966720585",
            "count": 0
        },
        {
            "id": "100085259528865",
            "count": 0
        },
        {
            "id": "61554675710700",
            "count": 34
        },
        {
            "id": "61554928105224",
            "count": 0
        },
        {
            "id": "100078889791326",
            "count": 0
        },
        {
            "id": "100082078660502",
            "count": 0
        },
        {
            "id": "100093666380820",
            "count": 3
        },
        {
            "id": "100085934521377",
            "count": 0
        },
        {
            "id": "100088977319563",
            "count": 0
        },
        {
            "id": "100089897166596",
            "count": 0
        },
        {
            "id": "61552868182165",
            "count": 0
        },
        {
            "id": "100093352148971",
            "count": 0
        },
        {
            "id": "61555882580452",
            "count": 0
        },
        {
            "id": "61553342486430",
            "count": 0
        },
        {
            "id": "61556017607027",
            "count": 0
        },
        {
            "id": "100087371977776",
            "count": 0
        },
        {
            "id": "100081263356361",
            "count": 0
        },
        {
            "id": "100095396597874",
            "count": 0
        },
        {
            "id": "100083940201436",
            "count": 0
        },
        {
            "id": "61551995573780",
            "count": 0
        },
        {
            "id": "61556891618280",
            "count": 0
        },
        {
            "id": "61550497393470",
            "count": 0
        },
        {
            "id": "100090690968592",
            "count": 0
        },
        {
            "id": "61551361058912",
            "count": 0
        },
        {
            "id": "61551992015960",
            "count": 0
        },
        {
            "id": "100079300612769",
            "count": 0
        },
        {
            "id": "61554676625535",
            "count": 0
        },
        {
            "id": "100076805960914",
            "count": 0
        },
        {
            "id": "100090055263711",
            "count": 0
        },
        {
            "id": "100092671497583",
            "count": 0
        },
        {
            "id": "61551053635413",
            "count": 0
        },
        {
            "id": "100091515476589",
            "count": 11
        },
        {
            "id": "61550902924150",
            "count": 0
        },
        {
            "id": "100082114500549",
            "count": 0
        },
        {
            "id": "100094921357761",
            "count": 0
        },
        {
            "id": "100093170903843",
            "count": 0
        },
        {
            "id": "61552302874397",
            "count": 0
        },
        {
            "id": "100093989171898",
            "count": 0
        },
        {
            "id": "61551081923004",
            "count": 0
        },
        {
            "id": "61557584044524",
            "count": 0
        },
        {
            "id": "100000622123483",
            "count": 0
        },
        {
            "id": "61557364617384",
            "count": 0
        },
        {
            "id": "61557579075059",
            "count": 0
        },
        {
            "id": "61555209135363",
            "count": 0
        },
        {
            "id": "61557589061861",
            "count": 0
        },
        {
            "id": "100023401686179",
            "count": 0
        },
        {
            "id": "61558474401296",
            "count": 1
        },
        {
            "id": "100085746765361",
            "count": 11
        },
        {
            "id": "61554329973761",
            "count": 0
        },
        {
            "id": "61555599504792",
            "count": 0
        },
        {
            "id": "61558624210490",
            "count": 0
        },
        {
            "id": "61557909327852",
            "count": 0
        },
        {
            "id": "61551391348333",
            "count": 35
        },
        {
            "id": "100084773303548",
            "count": 0
        },
        {
            "id": "100087893475366",
            "count": 0
        },
        {
            "id": "100092017008204",
            "count": 0
        },
        {
            "id": "100090142852075",
            "count": 0
        },
        {
            "id": "100084378103510",
            "count": 0
        },
        {
            "id": "61559545493006",
            "count": 0
        },
        {
            "id": "61559532861411",
            "count": 0
        },
        {
            "id": "100093624729133",
            "count": 0
        },
        {
            "id": "100093051642489",
            "count": 0
        },
        {
            "id": "61552411872970",
            "count": 11
        },
        {
            "id": "100089205454472",
            "count": 0
        },
        {
            "id": "100094760988409",
            "count": 0
        },
        {
            "id": "61559070333013",
            "count": 0
        },
        {
            "id": "100056611101316",
            "count": 0
        },
        {
            "id": "61557664555309",
            "count": 0
        },
        {
            "id": "100091971812462",
            "count": 0
        },
        {
            "id": "100073758246102",
            "count": 0
        },
        {
            "id": "61559777633272",
            "count": 35
        },
        {
            "id": "61559856307178",
            "count": 0
        },
        {
            "id": "61555962316369",
            "count": 0
        },
        {
            "id": "61550740599649",
            "count": 0
        },
        {
            "id": "61555856079604",
            "count": 0
        },
        {
            "id": "61557169396593",
            "count": 0
        },
        {
            "id": "61554657060164",
            "count": 0
        },
        {
            "id": "61550314954495",
            "count": 0
        },
        {
            "id": "61556358576535",
            "count": 0
        },
        {
            "id": "61558192455401",
            "count": 12
        },
        {
            "id": "61553928123305",
            "count": 0
        },
        {
            "id": "100077082825707",
            "count": 0
        },
        {
            "id": "61557623488042",
            "count": 35
        },
        {
            "id": "61560523033775",
            "count": 2
        },
        {
            "id": "61557990792452",
            "count": 2
        },
        {
            "id": "61557862673264",
            "count": 16
        },
        {
            "id": "61550555437615",
            "count": 4
        },
        {
            "id": "61555707685869",
            "count": 10
        }
    ],
    "time": 4,
    "last": {
        "time": 0,
        "day": [
            {
                "id": "61554417757153",
                "count": 0
            },
            {
                "id": "100094084096155",
                "count": 0
            },
            {
                "id": "61556309255001",
                "count": 0
            },
            {
                "id": "61555819021860",
                "count": 0
            },
            {
                "id": "61552626372533",
                "count": 0
            },
            {
                "id": "61554500413279",
                "count": 0
            },
            {
                "id": "61551244611327",
                "count": 0
            },
            {
                "id": "100093463959638",
                "count": 0
            },
            {
                "id": "61556986434152",
                "count": 0
            },
            {
                "id": "100007634802847",
                "count": 0
            },
            {
                "id": "100092331823627",
                "count": 0
            },
            {
                "id": "61550692794754",
                "count": 0
            },
            {
                "id": "61552353291750",
                "count": 0
            },
            {
                "id": "61554873957944",
                "count": 0
            },
            {
                "id": "100080672973218",
                "count": 0
            },
            {
                "id": "61555966720585",
                "count": 0
            },
            {
                "id": "100085259528865",
                "count": 0
            },
            {
                "id": "61554675710700",
                "count": 0
            },
            {
                "id": "61554928105224",
                "count": 0
            },
            {
                "id": "100078889791326",
                "count": 0
            },
            {
                "id": "100082078660502",
                "count": 0
            },
            {
                "id": "100093666380820",
                "count": 0
            },
            {
                "id": "100085934521377",
                "count": 0
            },
            {
                "id": "100088977319563",
                "count": 0
            },
            {
                "id": "100089897166596",
                "count": 0
            },
            {
                "id": "61552868182165",
                "count": 0
            },
            {
                "id": "100093352148971",
                "count": 0
            },
            {
                "id": "61555882580452",
                "count": 0
            },
            {
                "id": "61553342486430",
                "count": 0
            },
            {
                "id": "61556017607027",
                "count": 0
            },
            {
                "id": "100087371977776",
                "count": 0
            },
            {
                "id": "100081263356361",
                "count": 0
            },
            {
                "id": "100095396597874",
                "count": 0
            },
            {
                "id": "100083940201436",
                "count": 0
            },
            {
                "id": "61551995573780",
                "count": 0
            },
            {
                "id": "61556891618280",
                "count": 0
            },
            {
                "id": "61550497393470",
                "count": 0
            },
            {
                "id": "100090690968592",
                "count": 0
            },
            {
                "id": "61551361058912",
                "count": 0
            },
            {
                "id": "61551992015960",
                "count": 0
            },
            {
                "id": "100079300612769",
                "count": 0
            },
            {
                "id": "61554676625535",
                "count": 0
            },
            {
                "id": "100076805960914",
                "count": 0
            },
            {
                "id": "100090055263711",
                "count": 0
            },
            {
                "id": "100092671497583",
                "count": 0
            },
            {
                "id": "61551053635413",
                "count": 0
            },
            {
                "id": "100091515476589",
                "count": 0
            },
            {
                "id": "61550902924150",
                "count": 0
            },
            {
                "id": "100082114500549",
                "count": 0
            },
            {
                "id": "100094921357761",
                "count": 0
            },
            {
                "id": "100093170903843",
                "count": 0
            },
            {
                "id": "61552302874397",
                "count": 0
            },
            {
                "id": "100093989171898",
                "count": 0
            },
            {
                "id": "61551081923004",
                "count": 0
            },
            {
                "id": "61557584044524",
                "count": 0
            },
            {
                "id": "100000622123483",
                "count": 0
            },
            {
                "id": "61557364617384",
                "count": 0
            },
            {
                "id": "61557579075059",
                "count": 0
            },
            {
                "id": "61555209135363",
                "count": 0
            },
            {
                "id": "61557589061861",
                "count": 0
            },
            {
                "id": "100023401686179",
                "count": 0
            },
            {
                "id": "61558474401296",
                "count": 0
            },
            {
                "id": "100085746765361",
                "count": 0
            },
            {
                "id": "61554329973761",
                "count": 0
            },
            {
                "id": "61555599504792",
                "count": 0
            },
            {
                "id": "61558624210490",
                "count": 0
            },
            {
                "id": "61557909327852",
                "count": 0
            },
            {
                "id": "61551391348333",
                "count": 0
            },
            {
                "id": "100084773303548",
                "count": 0
            },
            {
                "id": "100087893475366",
                "count": 0
            },
            {
                "id": "100092017008204",
                "count": 0
            },
            {
                "id": "100090142852075",
                "count": 0
            },
            {
                "id": "100084378103510",
                "count": 0
            },
            {
                "id": "61559545493006",
                "count": 0
            },
            {
                "id": "61559532861411",
                "count": 0
            },
            {
                "id": "100093624729133",
                "count": 0
            },
            {
                "id": "100093051642489",
                "count": 0
            },
            {
                "id": "61552411872970",
                "count": 0
            },
            {
                "id": "100089205454472",
                "count": 0
            },
            {
                "id": "100094760988409",
                "count": 0
            },
            {
                "id": "61559070333013",
                "count": 0
            },
            {
                "id": "61555707685869",
                "count": 0
            },
            {
                "id": "100056611101316",
                "count": 0
            },
            {
                "id": "61557664555309",
                "count": 0
            },
            {
                "id": "100091971812462",
                "count": 0
            },
            {
                "id": "100073758246102",
                "count": 0
            },
            {
                "id": "61559777633272",
                "count": 0
            },
            {
                "id": "61559856307178",
                "count": 0
            },
            {
                "id": "61555962316369",
                "count": 0
            },
            {
                "id": "61550740599649",
                "count": 0
            },
            {
                "id": "61555856079604",
                "count": 0
            },
            {
                "id": "61557169396593",
                "count": 0
            },
            {
                "id": "61554657060164",
                "count": 0
            },
            {
                "id": "61550314954495",
                "count": 0
            },
            {
                "id": "61556358576535",
                "count": 0
            },
            {
                "id": "61558192455401",
                "count": 0
            },
            {
                "id": "61553928123305",
                "count": 0
            },
            {
                "id": "100077082825707",
                "count": 0
            },
            {
                "id": "61557623488042",
                "count": 0
            },
            {
                "id": "61560523033775",
                "count": 0
            },
            {
                "id": "61557990792452",
                "count": 0
            },
            {
                "id": "61557862673264",
                "count": 0
            },
            {
                "id": "61550555437615",
                "count": 0
            }
        ],
        "week": [
            {
                "id": "61554417757153",
                "count": 0
            },
            {
                "id": "100094084096155",
                "count": 0
            },
            {
                "id": "61556309255001",
                "count": 0
            },
            {
                "id": "61555819021860",
                "count": 0
            },
            {
                "id": "61552626372533",
                "count": 0
            },
            {
                "id": "61554500413279",
                "count": 0
            },
            {
                "id": "61551244611327",
                "count": 0
            },
            {
                "id": "100093463959638",
                "count": 0
            },
            {
                "id": "61556986434152",
                "count": 0
            },
            {
                "id": "100007634802847",
                "count": 0
            },
            {
                "id": "100092331823627",
                "count": 0
            },
            {
                "id": "61550692794754",
                "count": 0
            },
            {
                "id": "61552353291750",
                "count": 0
            },
            {
                "id": "61554873957944",
                "count": 0
            },
            {
                "id": "100080672973218",
                "count": 0
            },
            {
                "id": "61555966720585",
                "count": 0
            },
            {
                "id": "100085259528865",
                "count": 0
            },
            {
                "id": "61554675710700",
                "count": 0
            },
            {
                "id": "61554928105224",
                "count": 0
            },
            {
                "id": "100078889791326",
                "count": 0
            },
            {
                "id": "100082078660502",
                "count": 0
            },
            {
                "id": "100093666380820",
                "count": 0
            },
            {
                "id": "100085934521377",
                "count": 0
            },
            {
                "id": "100088977319563",
                "count": 0
            },
            {
                "id": "100089897166596",
                "count": 0
            },
            {
                "id": "61552868182165",
                "count": 0
            },
            {
                "id": "100093352148971",
                "count": 0
            },
            {
                "id": "61555882580452",
                "count": 0
            },
            {
                "id": "61553342486430",
                "count": 0
            },
            {
                "id": "61556017607027",
                "count": 0
            },
            {
                "id": "100087371977776",
                "count": 0
            },
            {
                "id": "100081263356361",
                "count": 0
            },
            {
                "id": "100095396597874",
                "count": 0
            },
            {
                "id": "100083940201436",
                "count": 0
            },
            {
                "id": "61551995573780",
                "count": 0
            },
            {
                "id": "61556891618280",
                "count": 0
            },
            {
                "id": "61550497393470",
                "count": 0
            },
            {
                "id": "100090690968592",
                "count": 0
            },
            {
                "id": "61551361058912",
                "count": 0
            },
            {
                "id": "61551992015960",
                "count": 0
            },
            {
                "id": "100079300612769",
                "count": 0
            },
            {
                "id": "61554676625535",
                "count": 0
            },
            {
                "id": "100076805960914",
                "count": 0
            },
            {
                "id": "100090055263711",
                "count": 0
            },
            {
                "id": "100092671497583",
                "count": 0
            },
            {
                "id": "61551053635413",
                "count": 0
            },
            {
                "id": "100091515476589",
                "count": 0
            },
            {
                "id": "61550902924150",
                "count": 0
            },
            {
                "id": "100082114500549",
                "count": 0
            },
            {
                "id": "100094921357761",
                "count": 0
            },
            {
                "id": "100093170903843",
                "count": 0
            },
            {
                "id": "61552302874397",
                "count": 0
            },
            {
                "id": "100093989171898",
                "count": 0
            },
            {
                "id": "61551081923004",
                "count": 0
            },
            {
                "id": "61557584044524",
                "count": 0
            },
            {
                "id": "100000622123483",
                "count": 0
            },
            {
                "id": "61557364617384",
                "count": 0
            },
            {
                "id": "61557579075059",
                "count": 0
            },
            {
                "id": "61555209135363",
                "count": 0
            },
            {
                "id": "61557589061861",
                "count": 0
            },
            {
                "id": "100023401686179",
                "count": 0
            },
            {
                "id": "61558474401296",
                "count": 0
            },
            {
                "id": "100085746765361",
                "count": 0
            },
            {
                "id": "61554329973761",
                "count": 0
            },
            {
                "id": "61555599504792",
                "count": 0
            },
            {
                "id": "61558624210490",
                "count": 0
            },
            {
                "id": "61557909327852",
                "count": 0
            },
            {
                "id": "61551391348333",
                "count": 0
            },
            {
                "id": "100084773303548",
                "count": 0
            },
            {
                "id": "100087893475366",
                "count": 0
            },
            {
                "id": "100092017008204",
                "count": 0
            },
            {
                "id": "100090142852075",
                "count": 0
            },
            {
                "id": "100084378103510",
                "count": 0
            },
            {
                "id": "61559545493006",
                "count": 0
            },
            {
                "id": "61559532861411",
                "count": 0
            },
            {
                "id": "100093624729133",
                "count": 0
            },
            {
                "id": "100093051642489",
                "count": 0
            },
            {
                "id": "61552411872970",
                "count": 0
            },
            {
                "id": "100089205454472",
                "count": 0
            },
            {
                "id": "100094760988409",
                "count": 0
            },
            {
                "id": "61559070333013",
                "count": 0
            },
            {
                "id": "61555707685869",
                "count": 0
            },
            {
                "id": "100056611101316",
                "count": 0
            },
            {
                "id": "61557664555309",
                "count": 0
            },
            {
                "id": "100091971812462",
                "count": 0
            },
            {
                "id": "100073758246102",
                "count": 0
            },
            {
                "id": "61559777633272",
                "count": 0
            },
            {
                "id": "61559856307178",
                "count": 0
            },
            {
                "id": "61555962316369",
                "count": 0
            },
            {
                "id": "61550740599649",
                "count": 0
            },
            {
                "id": "61555856079604",
                "count": 0
            },
            {
                "id": "61557169396593",
                "count": 0
            },
            {
                "id": "61554657060164",
                "count": 0
            },
            {
                "id": "61550314954495",
                "count": 0
            },
            {
                "id": "61556358576535",
                "count": 0
            },
            {
                "id": "61558192455401",
                "count": 0
            },
            {
                "id": "61553928123305",
                "count": 0
            },
            {
                "id": "100077082825707",
                "count": 0
            },
            {
                "id": "61557623488042",
                "count": 0
            },
            {
                "id": "61560523033775",
                "count": 0
            },
            {
                "id": "61557990792452",
                "count": 0
            },
            {
                "id": "61557862673264",
                "count": 0
            },
            {
                "id": "61550555437615",
                "count": 0
            }
        ]
    }
}